{"cameraMode":{"drawMode":0,"name":"Shaded","section":"Shading Mode"},"sceneLighting":true,"audioPlay":false,"sceneViewState":{"m_AlwaysRefresh":false,"showFog":true,"showSkybox":true,"showFlares":true,"showImageEffects":true,"showParticleSystems":true,"showVisualEffectGraphs":true,"m_FxEnabled":true},"in2DMode":false,"pivot":{"x":24.75,"y":25.470001220703126,"z":-72.05999755859375},"rotation":{"x":-0.1318240761756897,"y":-0.03954363986849785,"z":0.005264297593384981,"w":-0.9905115365982056},"size":38.914798736572269,"orthographic":false}